{
  "videos": [
    {
      "video_id": "UWdlnTlknPo",
      "title": "Шопен и польская музыка 🇵🇱 #shorts",
      "topic": "",
      "tags": [
        "польша",
        "явпольше",
        "shorts",
        "музыка",
        "торунь",
        "шопен",
        "польская музыка",
        "путешествия",
        "интересно",
        "европа",
        "факты",
        "кухня",
        "культура"
      ],
      "uploaded_at": "2026-03-16T08:54:26.980579+00:00",
      "stats": null
    },
    {
      "video_id": "kTrTFzVWMio",
      "title": "Природа Кракова 🌳🇵🇱 #shorts",
      "topic": "",
      "tags": [
        "польша",
        "явпольше",
        "shorts",
        "природа",
        "краков",
        "парки",
        "naturelover",
        "польскаприрода",
        "краковприрода",
        "nationalparks",
        "путешествия",
        "интересно",
        "европа",
        "факты",
        "кухня",
        "культура"
      ],
      "uploaded_at": "2026-03-16T12:58:56.891935+00:00",
      "stats": null
    },
    {
      "video_id": "otfdqDQ_6lU",
      "title": "Величка: подземный собор 🇵🇱 #shorts",
      "topic": "",
      "tags": [
        "польша",
        "явпольше",
        "shorts",
        "Величка",
        "подземныйсобор",
        "солянойсобор",
        "Краков",
        "туризм",
        "польскийтуризм",
        "путешествия",
        "интересно",
        "европа",
        "факты",
        "кухня",
        "культура"
      ],
      "uploaded_at": "2026-03-16T17:05:48.169537+00:00",
      "stats": null
    },
    {
      "video_id": "16hB0laGDPw",
      "title": "Увольнение в Польше 🇵🇱",
      "topic": "Как расторгнуть умову о праце и уволиться с работы в Польше без отработки?",
      "tags": [
        "польша",
        "явпольше",
        "увольнение",
        "трудовой договор",
        "права работников",
        "отработка",
        "сроки уведомления",
        "документы",
        "путешествия",
        "европа",
        "иммиграция",
        "жизньвпольше",
        "полезно"
      ],
      "uploaded_at": "2026-03-17T10:34:06.354171+00:00",
      "stats": null
    },
    {
      "video_id": "gEGF8UbwvaE",
      "title": "Лодзь — польский Голливуд 🇵🇱 #shorts",
      "topic": "",
      "tags": [
        "польша",
        "явпольше",
        "shorts",
        "лодзь",
        "уличноеИскусство",
        "польскийГолливуд",
        "туризм",
        "культура",
        "искусство",
        "голливуд",
        "путешествия",
        "интересно",
        "европа",
        "факты",
        "кухня"
      ],
      "uploaded_at": "2026-03-17T10:58:47.342795+00:00",
      "stats": null
    }
  ]
}